smclarify/COMMIT_HASH
smclarify/__init__.py
smclarify/bias/__init__.py
smclarify/bias/report.py
smclarify/bias/metrics/__init__.py
smclarify/bias/metrics/basic_stats.py
smclarify/bias/metrics/common.py
smclarify/bias/metrics/constants.py
smclarify/bias/metrics/posttraining.py
smclarify/bias/metrics/pretraining.py
smclarify/bias/metrics/registry.py
smclarify/util/__init__.py
smclarify/util/dataset.py
smclarify-0.4.dist-info/LICENSE
smclarify-0.4.dist-info/METADATA
smclarify-0.4.dist-info/NOTICE
smclarify-0.4.dist-info/WHEEL
smclarify-0.4.dist-info/top_level.txt
smclarify-0.4.dist-info/RECORD
