Metadata-Version: 2.1
Name: smclarify
Version: 0.4
Summary: UNKNOWN
Home-page: UNKNOWN
License: UNKNOWN
Platform: UNKNOWN
Classifier: Development Status :: 1 - Planning
Classifier: Intended Audience :: Developers
Classifier: Natural Language :: English
Classifier: Programming Language :: Python
Classifier: Programming Language :: Python :: 3.7
Classifier: Programming Language :: Python :: 3.8
Classifier: Programming Language :: Python :: 3.9
Classifier: Programming Language :: Python :: 3.10
Requires-Python: >=3.7
License-File: LICENSE
License-File: NOTICE
Requires-Dist: boto3
Requires-Dist: pyarrow
Requires-Dist: pandas
Requires-Dist: s3fs
Requires-Dist: numpy
Requires-Dist: scikit-learn
Requires-Dist: pyfunctional
Provides-Extra: test
Requires-Dist: tox ; extra == 'test'
Requires-Dist: flake8 ; extra == 'test'
Requires-Dist: black (==22.3.0) ; extra == 'test'
Requires-Dist: mock ; extra == 'test'
Requires-Dist: pre-commit ; extra == 'test'
Requires-Dist: pytest ; extra == 'test'
Requires-Dist: pytest-pspec ; extra == 'test'
Requires-Dist: sphinx ; extra == 'test'
Requires-Dist: coverage ; extra == 'test'
Requires-Dist: nbconvert ; extra == 'test'
Requires-Dist: jupyter ; extra == 'test'
Requires-Dist: jupyter-contrib-nbextensions ; extra == 'test'
Requires-Dist: seaborn ; extra == 'test'
Requires-Dist: mypy ; extra == 'test'
Requires-Dist: lxml ; extra == 'test'
